picogram/__init__.py
picogram/main.py
picogram/version.py
picogram-0.0.1.dist-info/METADATA
picogram-0.0.1.dist-info/WHEEL
picogram-0.0.1.dist-info/licenses/LICENSE
picogram-0.0.1.dist-info/RECORD
